{"type":"FeatureCollection", "features": [
{"type":"Feature","geometry":{"type":"Point","coordinates":[383218.3869803862,4164003.9204722065]},"properties":{"NOMBRE":"Asociación de Comerciantes de Baena (ACOBA)","COD_MUN":"14850","COD_ENT":"s44"}},
{"type":"Feature","geometry":{"type":"Point","coordinates":[372421.8059075666,4148364.146804365]},"properties":{"NOMBRE":"Asociación de Empresarios y Comerciantes de Cabra (AECA)","COD_MUN":"14940","COD_ENT":"s44"}},
{"type":"Feature","geometry":{"type":"Point","coordinates":[342334.2403794134,4193954.0472199717]},"properties":{"NOMBRE":"Asociación de Empresarios y Comerciantes de Occidente y Ciudad Jardin (ADECO)","COD_MUN":"14004","COD_ENT":"s44"}},
{"type":"Feature","geometry":{"type":"Point","coordinates":[343377.74628348334,4194662.742742852]},"properties":{"NOMBRE":"Asoc del Centro Comercial Abierto Centro Cordoba","COD_MUN":"14008","COD_ENT":"s44"}},
{"type":"Feature","geometry":{"type":"Point","coordinates":[346739.16731336835,4163871.8289928846]},"properties":{"NOMBRE":"Asociación del Comercio de la Rambla","COD_MUN":"14540","COD_ENT":"s44"}},
{"type":"Feature","geometry":{"type":"Point","coordinates":[355313.19977260125,4161382.9735815083]},"properties":{"NOMBRE":"Asociación de Empresarios de Montilla","COD_MUN":"14550","COD_ENT":"s44"}},
{"type":"Feature","geometry":{"type":"Point","coordinates":[301778.6304463246,4241488.742851273]},"properties":{"NOMBRE":"Asociación del Centro Comercial Abierto \"guadiamart\" de Peñarroya","COD_MUN":"14200","COD_ENT":"s44"}},
{"type":"Feature","geometry":{"type":"Point","coordinates":[338625.0297130895,4249489.46514677]},"properties":{"NOMBRE":"Asociación de Empresarios de Pozoblanco (ADEPO)","COD_MUN":"14400","COD_ENT":"s44"}},
{"type":"Feature","geometry":{"type":"Point","coordinates":[394273.3501207622,4144179.269762838]},"properties":{"NOMBRE":"Asociación de Comercio y Hosteleria de Priego Centro Comercial Abierto","COD_MUN":"14800","COD_ENT":"s44"}},
{"type":"Feature","geometry":{"type":"Point","coordinates":[247795.7900618606,4136090.731464359]},"properties":{"NOMBRE":"Asociación de Comerciantes de Alcala de Guadaira","COD_MUN":"41500","COD_ENT":"s44"}},
{"type":"Feature","geometry":{"type":"Point","coordinates":[240704.6416821254,4130266.2221205076]},"properties":{"NOMBRE":"Federacion Nazarena de Comerciantes","COD_MUN":"41700","COD_ENT":"s44"}},
{"type":"Feature","geometry":{"type":"Point","coordinates":[316240.09979675175,4156924.5248699747]},"properties":{"NOMBRE":"Asociación de Comerciantes Integrados en el Centro Comercial Abierto de Ecija","COD_MUN":"41400","COD_ENT":"s44"}},
{"type":"Feature","geometry":{"type":"Point","coordinates":[236343.20925300702,4141991.453633596]},"properties":{"NOMBRE":"Asociación de Comerciantes de la Calle Luis Montoto","COD_MUN":"41005","COD_ENT":"s44"}},
{"type":"Feature","geometry":{"type":"Point","coordinates":[237593.74210440763,4141467.1270524845]},"properties":{"NOMBRE":"Asociación de Comerciantes Marqués de Pickman Gran Plaza","COD_MUN":"41005","COD_ENT":"s44"}},
{"type":"Feature","geometry":{"type":"Point","coordinates":[225820.30536165775,4090366.905767694]},"properties":{"NOMBRE":"Asociación de Pequeños y Medianos Empresarios de Lebrija","COD_MUN":"41740","COD_ENT":"s44"}},
{"type":"Feature","geometry":{"type":"Point","coordinates":[149360.3128152279,4130654.005354617]},"properties":{"NOMBRE":"Agrupacion de Comerciantes E Industriales de las Calles del Centro","COD_MUN":"21001","COD_ENT":"s44"}},
{"type":"Feature","geometry":{"type":"Point","coordinates":[575611.5419404382,4138275.046033822]},"properties":{"NOMBRE":"Asociación de Empresarios y Profesionales de Albox  Valle del Almanzora","COD_MUN":"04800","COD_ENT":"s44"}},
{"type":"Feature","geometry":{"type":"Point","coordinates":[547835.205851286,4077154.9007103876]},"properties":{"NOMBRE":"Asociación de Comerciantes del Centro Comercial Abierto Almeria Centro","COD_MUN":"04001","COD_ENT":"s44"}},
{"type":"Feature","geometry":{"type":"Point","coordinates":[446625.8064610332,4114433.8385888934]},"properties":{"NOMBRE":"Asociación Empresarios de Comercio, Industria, Servicios y Profes. Centro Granada","COD_MUN":"18001","COD_ENT":"s44"}},
{"type":"Feature","geometry":{"type":"Point","coordinates":[599415.1520778503,4128223.5455121645]},"properties":{"NOMBRE":"Asociación de Empresarios y Comerciantes de Cuevas del Almanzora (ASEMCAL)","COD_MUN":"04610","COD_ENT":"s44"}},
{"type":"Feature","geometry":{"type":"Point","coordinates":[534426.7874746275,4068614.7601199294]},"properties":{"NOMBRE":"Asociación de Comerciantes Urbanización de Roquetas de Mar","COD_MUN":"04740","COD_ENT":"s44"}},
{"type":"Feature","geometry":{"type":"Point","coordinates":[438321.70663856214,4065607.904248365]},"properties":{"NOMBRE":"Asociación de Comercio Cca  Almuñécar\r\n","COD_MUN":"18690","COD_ENT":"s44"}},
{"type":"Feature","geometry":{"type":"Point","coordinates":[488187.90414553176,4128324.8406253285]},"properties":{"NOMBRE":"Asociación Local de Comercio de Guadix","COD_MUN":"18500","COD_ENT":"s44"}},
{"type":"Feature","geometry":{"type":"Point","coordinates":[407057.57856523857,4117242.0773417875]},"properties":{"NOMBRE":"Asociación de Empresarios de la Mancomunidad de Municipios \"Ribera Baja del Genil\"","COD_MUN":"18360","COD_ENT":"s44"}},
{"type":"Feature","geometry":{"type":"Point","coordinates":[398072.88753006124,4114008.1717687566]},"properties":{"NOMBRE":"Asociación Lojeña de Comercio","COD_MUN":"18300","COD_ENT":"s44"}},
{"type":"Feature","geometry":{"type":"Point","coordinates":[453711.2999477812,4066747.5195792248]},"properties":{"NOMBRE":"Asociación de Comerciantes del Centro de Motril","COD_MUN":"18600","COD_ENT":"s44"}},
{"type":"Feature","geometry":{"type":"Point","coordinates":[436350.5966392221,4116191.5208089557]},"properties":{"NOMBRE":"Asociación de Empresarios de Santa Fe","COD_MUN":"18320","COD_ENT":"s44"}},
{"type":"Feature","geometry":{"type":"Point","coordinates":[204853.11800796277,4048008.601045923]},"properties":{"NOMBRE":"Cadiz Centro Club de Calidad","COD_MUN":"11001","COD_ENT":"s44"}},
{"type":"Feature","geometry":{"type":"Point","coordinates":[193263.23641338764,4071447.9752631728]},"properties":{"NOMBRE":"Asociación de Comerciantes e Industriales de Chipiona","COD_MUN":"11550","COD_ENT":"s44"}},
{"type":"Feature","geometry":{"type":"Point","coordinates":[222485.632228281,4019342.445449527]},"properties":{"NOMBRE":"Asociación \"Comerciantes y Fabricantes de Artesania de Conil\"","COD_MUN":"11140","COD_ENT":"s44"}},
{"type":"Feature","geometry":{"type":"Point","coordinates":[211318.34231158544,4055182.1340548624]},"properties":{"NOMBRE":"Asociación de Comerciantes del Puerto","COD_MUN":"11500","COD_ENT":"s44"}},
{"type":"Feature","geometry":{"type":"Point","coordinates":[219720.76716353238,4064238.8686628933]},"properties":{"NOMBRE":"Asociación de Comerciantes del Centro de Jerez (ACOJE)","COD_MUN":"11402","COD_ENT":"s44"}},
{"type":"Feature","geometry":{"type":"Point","coordinates":[288476.18946397665,4004539.1451680725]},"properties":{"NOMBRE":"Asociacion de Comerciantes del Centro de la Línea","COD_MUN":"11300","COD_ENT":"s44"}},
{"type":"Feature","geometry":{"type":"Point","coordinates":[213586.39056388813,4040529.3197131045]},"properties":{"NOMBRE":"Asociación de Comerciantes de San Fernando -ACOSAFE-","COD_MUN":"11100","COD_ENT":"s44"}},
{"type":"Feature","geometry":{"type":"Point","coordinates":[418266.25420519564,4146753.7457000213]},"properties":{"NOMBRE":"Agrupacion Centro Comercial Abierto de Alcalá la Real","COD_MUN":"23680","COD_ENT":"s44"}},
{"type":"Feature","geometry":{"type":"Point","coordinates":[458857.2013490909,4205170.090499627]},"properties":{"NOMBRE":"Asociación Baezana de Industria Servicios y Comercio","COD_MUN":"23440","COD_ENT":"s44"}},
{"type":"Feature","geometry":{"type":"Point","coordinates":[430414.3025770689,4180532.495221619]},"properties":{"NOMBRE":"Asociación de Comerciantes las Palmeras","COD_MUN":"23003","COD_ENT":"s44"}},
{"type":"Feature","geometry":{"type":"Point","coordinates":[446176.5276483892,4236411.861592246]},"properties":{"NOMBRE":"Asociación Comarcal de Comerciantes de la Carolina","COD_MUN":"23200","COD_ENT":"s44"}},
{"type":"Feature","geometry":{"type":"Point","coordinates":[444222.39089152083,4216666.350466042]},"properties":{"NOMBRE":"Asociacion de Comerciantes E Industriales de Linares","COD_MUN":"23700","COD_ENT":"s44"}},
{"type":"Feature","geometry":{"type":"Point","coordinates":[414289.6848400543,4174904.199951164]},"properties":{"NOMBRE":"Asociacion Empresarial Marteña","COD_MUN":"23600","COD_ENT":"s44"}},
{"type":"Feature","geometry":{"type":"Point","coordinates":[467413.13306439586,4207298.173744803]},"properties":{"NOMBRE":"Asociación Local del Comercio Industria y Servicios de Ubeda","COD_MUN":"23400","COD_ENT":"s44"}},
{"type":"Feature","geometry":{"type":"Point","coordinates":[349039.7346871543,4056701.6834109346]},"properties":{"NOMBRE":"Asociación de Empresarios de Alhaurin Grande","COD_MUN":"29120","COD_ENT":"s44"}},
{"type":"Feature","geometry":{"type":"Point","coordinates":[347874.2153835824,4076731.7346743946]},"properties":{"NOMBRE":"Asociación Empresarios y Comerciantes de Álora","COD_MUN":"29500","COD_ENT":"s44"}},
{"type":"Feature","geometry":{"type":"Point","coordinates":[361291.25116449175,4098198.5043363892]},"properties":{"NOMBRE":"Asociación del Comercio E Industrias de Antequera","COD_MUN":"29200","COD_ENT":"s44"}},
{"type":"Feature","geometry":{"type":"Point","coordinates":[362799.72239878564,4051422.055397264]},"properties":{"NOMBRE":"Asociacion de Comerciantes y Empresarios de Benalmadena (ACEB)","COD_MUN":"29631","COD_ENT":"s44"}},
{"type":"Feature","geometry":{"type":"Point","coordinates":[342818.9119297673,4058550.9552838453]},"properties":{"NOMBRE":"Asociación de Jovenes Empresarios y Profesionales de Coín","COD_MUN":"29100","COD_ENT":"s44"}},
{"type":"Feature","geometry":{"type":"Point","coordinates":[307674.4211762963,4033457.1913940236]},"properties":{"NOMBRE":"Asociación de Empresarios de Estepona","COD_MUN":"29680","COD_ENT":"s44"}},
{"type":"Feature","geometry":{"type":"Point","coordinates":[372988.22358250263,4064858.324779515]},"properties":{"NOMBRE":"Asociación Centro Historico de Malaga","COD_MUN":"29005","COD_ENT":"s44"}},
{"type":"Feature","geometry":{"type":"Point","coordinates":[371283.64120059885,4063800.791097446]},"properties":{"NOMBRE":"Asociación de Empresarios y Comerciantes Cruz del Humilladero","COD_MUN":"29006","COD_ENT":"s44"}},
{"type":"Feature","geometry":{"type":"Point","coordinates":[331180.8510952306,4042181.7819832903]},"properties":{"NOMBRE":"Asociación de Comerciantes y Profesionales del Casco Antiguo de Marbella","COD_MUN":"29600","COD_ENT":"s44"}},
{"type":"Feature","geometry":{"type":"Point","coordinates":[421595.725119114,4067152.0474385396]},"properties":{"NOMBRE":"Asociacion Centro Comercial Abierto de Nerja","COD_MUN":"29780","COD_ENT":"s44"}},
{"type":"Feature","geometry":{"type":"Point","coordinates":[385186.14439551404,4064115.9864126174]},"properties":{"NOMBRE":"Asociación de Comerciantes y Empresarios del Municipio de R. de la V","COD_MUN":"29730","COD_ENT":"s44"}},
{"type":"Feature","geometry":{"type":"Point","coordinates":[306800.734398542,4068533.636339176]},"properties":{"NOMBRE":"Asociación Pequeña y Mediana Empresa de Ronda (APYMER)","COD_MUN":"29400","COD_ENT":"s44"}},
{"type":"Feature","geometry":{"type":"Point","coordinates":[401393.5623511943,4071238.1587835136]},"properties":{"NOMBRE":"Asociación de Comerciantes y Empresarios de Vélez-málaga","COD_MUN":"29700","COD_ENT":"s44"}},
{"type":"Feature","geometry":{"type":"Point","coordinates":[402350.3584920074,4066812.3412310425]},"properties":{"NOMBRE":"Asociación de Comerciantes y Empresarios de Torre del Mar","COD_MUN":"29740","COD_ENT":"s44"}},
{"type":"Feature","geometry":{"type":"Point","coordinates":[230317.28064954968,4140849.3761197184]},"properties":{"NOMBRE":"Asociacion de Comerciantes de Tomares Acopymetom Tomares","COD_MUN":"41093","COD_ENT":"s44"}}
]}